[
    {
        "id": "product1",
        "imgMain": "https://file.hstatic.net/1000280685/collection/1-7_dc4c9db64b6e42e6b6626eb15da0d581_medium.png",
        "imgHover": "https://product.hstatic.net/1000280685/product/ez__15__28665c7f5fbc4b85b2bc39b4c5bdd9a4_large.jpg",
        "imgDemo": [
            "https://file.hstatic.net/1000280685/collection/1-7_dc4c9db64b6e42e6b6626eb15da0d581_medium.png",
            "https://product.hstatic.net/1000280685/product/ez__15__28665c7f5fbc4b85b2bc39b4c5bdd9a4_large.jpg",
            "https://file.hstatic.net/1000280685/collection/1-7_dc4c9db64b6e42e6b6626eb15da0d581_medium.png",
            "https://product.hstatic.net/1000280685/product/ez__15__28665c7f5fbc4b85b2bc39b4c5bdd9a4_large.jpg",
            "https://file.hstatic.net/1000280685/collection/1-7_dc4c9db64b6e42e6b6626eb15da0d581_medium.png",
            "https://product.hstatic.net/1000280685/product/ez__15__28665c7f5fbc4b85b2bc39b4c5bdd9a4_large.jpg",
            "https://file.hstatic.net/1000280685/collection/1-7_dc4c9db64b6e42e6b6626eb15da0d581_medium.png",
            "https://product.hstatic.net/1000280685/product/ez__15__28665c7f5fbc4b85b2bc39b4c5bdd9a4_large.jpg"
        ],
        "productName": "HONEY Plus",
        "productDescription": "Bàn ăn, bàn làm việc lớn",
        "description": "<p><strong>M&agrave;u sắc: </strong>Xanh đậu</p><p><strong>K&iacute;ch thước sản phẩm: </strong>D100x R35 cm</p><p><strong>M&ocirc; tả sản phẩm:</strong> Vỏ gối được thiết kế c&oacute; kho&aacute; k&eacute;o dễ th&aacute;o vỏ hoặc lồng ruột gối.&nbsp;</p><p><strong>Chất liệu:&nbsp;</strong>100% Cotton 300 thread count</p><p><strong>Hướng dẫn sử dụng:</strong><br />- Kh&ocirc;ng n&ecirc;n ng&acirc;m sản phẩm.<br />- Kh&ocirc;ng giặt sản phẩm với c&aacute;c loại ho&aacute; chất c&oacute; chất tẩy mạnh.<br />- N&ecirc;n giặt bằng tay/giặt m&aacute;y chế độ nhẹ v&agrave; nhiệt độ b&igrave;nh thường.<br />- N&ecirc;n lật mặt tr&aacute;i sản phẩm, giặt ri&ecirc;ng theo m&agrave;u v&agrave; b&ecirc;n trong t&uacute;i giặt.<br />- N&ecirc;n phơi sản phẩm ở nơi tho&aacute;ng m&aacute;t, tr&aacute;nh &aacute;nh nắng trực tiếp.<br />- N&ecirc;n sấy kh&ocirc; hoặc ủi với nhiệt độ nhỏ hơn 110 độ C.<br />- Lưu &yacute;: Kh&ocirc;ng được ủi c&aacute;c sản phẩm chần g&ograve;n.</p><p>&nbsp;</p>",
        "price": "5190000",
        "priceDiscount": "",
        "wareHouse": "0"
    },
    {
        "id": "product2",
        "imgMain": "https://file.hstatic.net/1000280685/collection/seta_11_b3c8806dd4384251a178fdfbe74e2c1d_medium.jpg",
        "imgHover": "https://product.hstatic.net/1000280685/product/guong-medusa-thucte__6__c527b91078f04734bf003b6568cb22de_large.jpg",
        "imgDemo": [
            "https://file.hstatic.net/1000280685/collection/seta_11_b3c8806dd4384251a178fdfbe74e2c1d_medium.jpg",
            "https://product.hstatic.net/1000280685/product/guong-medusa-thucte__6__c527b91078f04734bf003b6568cb22de_large.jpg"
        ],
        "productName": "HONEY Plus",
        "productDescription": "Bàn ăn, bàn làm việc lớn",
        "description": "<p><strong>M&agrave;u sắc: </strong>Xanh đậu</p><p><strong>K&iacute;ch thước sản phẩm: </strong>D100x R35 cm</p><p><strong>M&ocirc; tả sản phẩm:</strong> Vỏ gối được thiết kế c&oacute; kho&aacute; k&eacute;o dễ th&aacute;o vỏ hoặc lồng ruột gối.&nbsp;</p><p><strong>Chất liệu:&nbsp;</strong>100% Cotton 300 thread count</p><p><strong>Hướng dẫn sử dụng:</strong><br />- Kh&ocirc;ng n&ecirc;n ng&acirc;m sản phẩm.<br />- Kh&ocirc;ng giặt sản phẩm với c&aacute;c loại ho&aacute; chất c&oacute; chất tẩy mạnh.<br />- N&ecirc;n giặt bằng tay/giặt m&aacute;y chế độ nhẹ v&agrave; nhiệt độ b&igrave;nh thường.<br />- N&ecirc;n lật mặt tr&aacute;i sản phẩm, giặt ri&ecirc;ng theo m&agrave;u v&agrave; b&ecirc;n trong t&uacute;i giặt.<br />- N&ecirc;n phơi sản phẩm ở nơi tho&aacute;ng m&aacute;t, tr&aacute;nh &aacute;nh nắng trực tiếp.<br />- N&ecirc;n sấy kh&ocirc; hoặc ủi với nhiệt độ nhỏ hơn 110 độ C.<br />- Lưu &yacute;: Kh&ocirc;ng được ủi c&aacute;c sản phẩm chần g&ograve;n.</p><p>&nbsp;</p>",
        "price": "1190000",
        "priceDiscount": "",
        "wareHouse": "100"
    },
    {
        "id": "product3",
        "imgMain": "https://file.hstatic.net/1000280685/collection/d_2_8221170094a14347bf25759743ece8d7_medium.jpg",
        "imgHover": "https://product.hstatic.net/1000280685/product/guong-mibo-thucte__2__3ea3904acf774296a57ec720fb107018_large.png",
        "imgDemo": [
            "https://file.hstatic.net/1000280685/collection/d_2_8221170094a14347bf25759743ece8d7_medium.jpg",
            "https://product.hstatic.net/1000280685/product/guong-mibo-thucte__2__3ea3904acf774296a57ec720fb107018_large.png"
        ],
        "productName": "SAGO",
        "productDescription": "Bàn ăn",
        "description": "<p><strong>M&agrave;u sắc: </strong>Xanh đậu</p><p><strong>K&iacute;ch thước sản phẩm: </strong>D100x R35 cm</p><p><strong>M&ocirc; tả sản phẩm:</strong> Vỏ gối được thiết kế c&oacute; kho&aacute; k&eacute;o dễ th&aacute;o vỏ hoặc lồng ruột gối.&nbsp;</p><p><strong>Chất liệu:&nbsp;</strong>100% Cotton 300 thread count</p><p><strong>Hướng dẫn sử dụng:</strong><br />- Kh&ocirc;ng n&ecirc;n ng&acirc;m sản phẩm.<br />- Kh&ocirc;ng giặt sản phẩm với c&aacute;c loại ho&aacute; chất c&oacute; chất tẩy mạnh.<br />- N&ecirc;n giặt bằng tay/giặt m&aacute;y chế độ nhẹ v&agrave; nhiệt độ b&igrave;nh thường.<br />- N&ecirc;n lật mặt tr&aacute;i sản phẩm, giặt ri&ecirc;ng theo m&agrave;u v&agrave; b&ecirc;n trong t&uacute;i giặt.<br />- N&ecirc;n phơi sản phẩm ở nơi tho&aacute;ng m&aacute;t, tr&aacute;nh &aacute;nh nắng trực tiếp.<br />- N&ecirc;n sấy kh&ocirc; hoặc ủi với nhiệt độ nhỏ hơn 110 độ C.<br />- Lưu &yacute;: Kh&ocirc;ng được ủi c&aacute;c sản phẩm chần g&ograve;n.</p><p>&nbsp;</p>",
        "price": "4550000",
        "priceDiscount": "",
        "wareHouse": "100"
    },
    {
        "id": "product4",
        "imgMain": "https://file.hstatic.net/1000280685/collection/profile_den_1_chan_6028ad525d5c49f782f103e9a80a66f8_medium.jpg",
        "imgHover": "https://product.hstatic.net/1000280685/product/ez_tuluutru_31_18f45d6d05314829a330db8254ffa5be_large.jpg",
        "imgDemo": [
            "https://file.hstatic.net/1000280685/collection/profile_den_1_chan_6028ad525d5c49f782f103e9a80a66f8_medium.jpg",

            "https://product.hstatic.net/1000280685/product/ez_tuluutru_31_18f45d6d05314829a330db8254ffa5be_large.jpg"
        ],
        "productName": "DALAT",
        "productDescription": "Bàn ăn",
        "description": "<p><strong>M&agrave;u sắc: </strong>Xanh đậu</p><p><strong>K&iacute;ch thước sản phẩm: </strong>D100x R35 cm</p><p><strong>M&ocirc; tả sản phẩm:</strong> Vỏ gối được thiết kế c&oacute; kho&aacute; k&eacute;o dễ th&aacute;o vỏ hoặc lồng ruột gối.&nbsp;</p><p><strong>Chất liệu:&nbsp;</strong>100% Cotton 300 thread count</p><p><strong>Hướng dẫn sử dụng:</strong><br />- Kh&ocirc;ng n&ecirc;n ng&acirc;m sản phẩm.<br />- Kh&ocirc;ng giặt sản phẩm với c&aacute;c loại ho&aacute; chất c&oacute; chất tẩy mạnh.<br />- N&ecirc;n giặt bằng tay/giặt m&aacute;y chế độ nhẹ v&agrave; nhiệt độ b&igrave;nh thường.<br />- N&ecirc;n lật mặt tr&aacute;i sản phẩm, giặt ri&ecirc;ng theo m&agrave;u v&agrave; b&ecirc;n trong t&uacute;i giặt.<br />- N&ecirc;n phơi sản phẩm ở nơi tho&aacute;ng m&aacute;t, tr&aacute;nh &aacute;nh nắng trực tiếp.<br />- N&ecirc;n sấy kh&ocirc; hoặc ủi với nhiệt độ nhỏ hơn 110 độ C.<br />- Lưu &yacute;: Kh&ocirc;ng được ủi c&aacute;c sản phẩm chần g&ograve;n.</p><p>&nbsp;</p>",
        "price": "15190000",
        "priceDiscount": "12590000",
        "wareHouse": "100"
    },
    {
        "id": "product5",
        "imgMain": "https://file.hstatic.net/1000280685/collection/p1_c87b122f8815425bb2c51a7584dd9ab6_medium.png",
        "imgHover": "https://product.hstatic.net/1000280685/product/ez__8__253a52fb9a60493ea43b85e1f5e8ca13_large.jpg",
        "imgDemo": [
            "https://file.hstatic.net/1000280685/collection/p1_c87b122f8815425bb2c51a7584dd9ab6_medium.png",

            "https://product.hstatic.net/1000280685/product/ez__8__253a52fb9a60493ea43b85e1f5e8ca13_large.jpg"
        ],
        "productName": "QLI",
        "productDescription": "Bàn ăn 4-6 người",
        "description": "<p><strong>M&agrave;u sắc: </strong>Xanh đậu</p><p><strong>K&iacute;ch thước sản phẩm: </strong>D100x R35 cm</p><p><strong>M&ocirc; tả sản phẩm:</strong> Vỏ gối được thiết kế c&oacute; kho&aacute; k&eacute;o dễ th&aacute;o vỏ hoặc lồng ruột gối.&nbsp;</p><p><strong>Chất liệu:&nbsp;</strong>100% Cotton 300 thread count</p><p><strong>Hướng dẫn sử dụng:</strong><br />- Kh&ocirc;ng n&ecirc;n ng&acirc;m sản phẩm.<br />- Kh&ocirc;ng giặt sản phẩm với c&aacute;c loại ho&aacute; chất c&oacute; chất tẩy mạnh.<br />- N&ecirc;n giặt bằng tay/giặt m&aacute;y chế độ nhẹ v&agrave; nhiệt độ b&igrave;nh thường.<br />- N&ecirc;n lật mặt tr&aacute;i sản phẩm, giặt ri&ecirc;ng theo m&agrave;u v&agrave; b&ecirc;n trong t&uacute;i giặt.<br />- N&ecirc;n phơi sản phẩm ở nơi tho&aacute;ng m&aacute;t, tr&aacute;nh &aacute;nh nắng trực tiếp.<br />- N&ecirc;n sấy kh&ocirc; hoặc ủi với nhiệt độ nhỏ hơn 110 độ C.<br />- Lưu &yacute;: Kh&ocirc;ng được ủi c&aacute;c sản phẩm chần g&ograve;n.</p><p>&nbsp;</p>",
        "price": "5790000",
        "priceDiscount": "",
        "wareHouse": "100"
    },
    {
        "id": "product6",
        "imgMain": "https://file.hstatic.net/1000280685/collection/2_6dc4cd1d4bcb47e4ae2bbf2ab2f8ed25_medium.jpg",
        "imgHover": "https://product.hstatic.net/1000280685/product/ez__15__28665c7f5fbc4b85b2bc39b4c5bdd9a4_large.jpg",
        "imgDemo": [
            "https://file.hstatic.net/1000280685/collection/2_6dc4cd1d4bcb47e4ae2bbf2ab2f8ed25_medium.jpg",

            "https://product.hstatic.net/1000280685/product/ez__15__28665c7f5fbc4b85b2bc39b4c5bdd9a4_large.jpg"
        ],
        "productName": "COTTON DYSANIA",
        "productDescription": "Combo 5 món",
        "description": "<p><strong>M&agrave;u sắc: </strong>Xanh đậu</p><p><strong>K&iacute;ch thước sản phẩm: </strong>D100x R35 cm</p><p><strong>M&ocirc; tả sản phẩm:</strong> Vỏ gối được thiết kế c&oacute; kho&aacute; k&eacute;o dễ th&aacute;o vỏ hoặc lồng ruột gối.&nbsp;</p><p><strong>Chất liệu:&nbsp;</strong>100% Cotton 300 thread count</p><p><strong>Hướng dẫn sử dụng:</strong><br />- Kh&ocirc;ng n&ecirc;n ng&acirc;m sản phẩm.<br />- Kh&ocirc;ng giặt sản phẩm với c&aacute;c loại ho&aacute; chất c&oacute; chất tẩy mạnh.<br />- N&ecirc;n giặt bằng tay/giặt m&aacute;y chế độ nhẹ v&agrave; nhiệt độ b&igrave;nh thường.<br />- N&ecirc;n lật mặt tr&aacute;i sản phẩm, giặt ri&ecirc;ng theo m&agrave;u v&agrave; b&ecirc;n trong t&uacute;i giặt.<br />- N&ecirc;n phơi sản phẩm ở nơi tho&aacute;ng m&aacute;t, tr&aacute;nh &aacute;nh nắng trực tiếp.<br />- N&ecirc;n sấy kh&ocirc; hoặc ủi với nhiệt độ nhỏ hơn 110 độ C.<br />- Lưu &yacute;: Kh&ocirc;ng được ủi c&aacute;c sản phẩm chần g&ograve;n.</p><p>&nbsp;</p>",
        "price": "1690000",
        "priceDiscount": "5590000",
        "wareHouse": "100"
    },
    {
        "id": "product7",
        "imgMain": "https://file.hstatic.net/1000280685/collection/a011_01_98adf64f2d57418fa681c6ab8b0c5f39_medium.jpg",
        "imgHover": "https://product.hstatic.net/1000280685/product/chin_trang__4__90cfc2c999c3437b8f0f87a127c57c90_large.png",
        "imgDemo": [
            "https://file.hstatic.net/1000280685/collection/a011_01_98adf64f2d57418fa681c6ab8b0c5f39_medium.jpg",

            "https://product.hstatic.net/1000280685/product/chin_trang__4__90cfc2c999c3437b8f0f87a127c57c90_large.png"
        ],
        "productName": "ALUS",
        "productDescription": "Ruột gối ôm chữ nhật premium",
        "description": "<p><strong>M&agrave;u sắc: </strong>Xanh đậu</p><p><strong>K&iacute;ch thước sản phẩm: </strong>D100x R35 cm</p><p><strong>M&ocirc; tả sản phẩm:</strong> Vỏ gối được thiết kế c&oacute; kho&aacute; k&eacute;o dễ th&aacute;o vỏ hoặc lồng ruột gối.&nbsp;</p><p><strong>Chất liệu:&nbsp;</strong>100% Cotton 300 thread count</p><p><strong>Hướng dẫn sử dụng:</strong><br />- Kh&ocirc;ng n&ecirc;n ng&acirc;m sản phẩm.<br />- Kh&ocirc;ng giặt sản phẩm với c&aacute;c loại ho&aacute; chất c&oacute; chất tẩy mạnh.<br />- N&ecirc;n giặt bằng tay/giặt m&aacute;y chế độ nhẹ v&agrave; nhiệt độ b&igrave;nh thường.<br />- N&ecirc;n lật mặt tr&aacute;i sản phẩm, giặt ri&ecirc;ng theo m&agrave;u v&agrave; b&ecirc;n trong t&uacute;i giặt.<br />- N&ecirc;n phơi sản phẩm ở nơi tho&aacute;ng m&aacute;t, tr&aacute;nh &aacute;nh nắng trực tiếp.<br />- N&ecirc;n sấy kh&ocirc; hoặc ủi với nhiệt độ nhỏ hơn 110 độ C.<br />- Lưu &yacute;: Kh&ocirc;ng được ủi c&aacute;c sản phẩm chần g&ograve;n.</p><p>&nbsp;</p>",
        "price": "190000",
        "priceDiscount": "590000",
        "wareHouse": "100"
    },
    {
        "id": "product8",
        "imgMain": "https://file.hstatic.net/1000280685/collection/p1-6_07d8ffe29dad4df4b67d47357be33d45_medium.png",
        "imgHover": "https://product.hstatic.net/1000280685/product/cotton_dysania_xamnhat__19__a9e260b226234eee8bb5847989c08455_large.png",
        "imgDemo": [
            "https://file.hstatic.net/1000280685/collection/p1-6_07d8ffe29dad4df4b67d47357be33d45_medium.png",

            "https://product.hstatic.net/1000280685/product/cotton_dysania_xamnhat__19__a9e260b226234eee8bb5847989c08455_large.png"
        ],
        "productName": "DOUX",
        "productDescription": "Ruột gối nằm standard",
        "description": "<p><strong>M&agrave;u sắc: </strong>Xanh đậu</p><p><strong>K&iacute;ch thước sản phẩm: </strong>D100x R35 cm</p><p><strong>M&ocirc; tả sản phẩm:</strong> Vỏ gối được thiết kế c&oacute; kho&aacute; k&eacute;o dễ th&aacute;o vỏ hoặc lồng ruột gối.&nbsp;</p><p><strong>Chất liệu:&nbsp;</strong>100% Cotton 300 thread count</p><p><strong>Hướng dẫn sử dụng:</strong><br />- Kh&ocirc;ng n&ecirc;n ng&acirc;m sản phẩm.<br />- Kh&ocirc;ng giặt sản phẩm với c&aacute;c loại ho&aacute; chất c&oacute; chất tẩy mạnh.<br />- N&ecirc;n giặt bằng tay/giặt m&aacute;y chế độ nhẹ v&agrave; nhiệt độ b&igrave;nh thường.<br />- N&ecirc;n lật mặt tr&aacute;i sản phẩm, giặt ri&ecirc;ng theo m&agrave;u v&agrave; b&ecirc;n trong t&uacute;i giặt.<br />- N&ecirc;n phơi sản phẩm ở nơi tho&aacute;ng m&aacute;t, tr&aacute;nh &aacute;nh nắng trực tiếp.<br />- N&ecirc;n sấy kh&ocirc; hoặc ủi với nhiệt độ nhỏ hơn 110 độ C.<br />- Lưu &yacute;: Kh&ocirc;ng được ủi c&aacute;c sản phẩm chần g&ograve;n.</p><p>&nbsp;</p>",
        "price": "90000",
        "priceDiscount": "",
        "wareHouse": "100"
    },
    {
        "id": "product9",
        "imgMain": "https://file.hstatic.net/1000280685/collection/profile-gio-do-black_d9ad3eb32365469688c6244364329f08_large_72e91275f967463294cb216e82db3c2d_medium.png",
        "imgHover": "https://product.hstatic.net/1000280685/product/xam_3_d088178cc53e49899a558d11a0c79b18_3768eadc53014f14b16b11ae1a96fc0c_large.jpg",
        "imgDemo": [
            "https://file.hstatic.net/1000280685/collection/profile-gio-do-black_d9ad3eb32365469688c6244364329f08_large_72e91275f967463294cb216e82db3c2d_medium.png",
            "https://product.hstatic.net/1000280685/product/xam_3_d088178cc53e49899a558d11a0c79b18_3768eadc53014f14b16b11ae1a96fc0c_large.jpg"
        ],
        "productName": "MOLA",
        "productDescription": "Ruột chăn standard ",
        "description": "<p><strong>M&agrave;u sắc: </strong>Xanh đậu</p><p><strong>K&iacute;ch thước sản phẩm: </strong>D100x R35 cm</p><p><strong>M&ocirc; tả sản phẩm:</strong> Vỏ gối được thiết kế c&oacute; kho&aacute; k&eacute;o dễ th&aacute;o vỏ hoặc lồng ruột gối.&nbsp;</p><p><strong>Chất liệu:&nbsp;</strong>100% Cotton 300 thread count</p><p><strong>Hướng dẫn sử dụng:</strong><br />- Kh&ocirc;ng n&ecirc;n ng&acirc;m sản phẩm.<br />- Kh&ocirc;ng giặt sản phẩm với c&aacute;c loại ho&aacute; chất c&oacute; chất tẩy mạnh.<br />- N&ecirc;n giặt bằng tay/giặt m&aacute;y chế độ nhẹ v&agrave; nhiệt độ b&igrave;nh thường.<br />- N&ecirc;n lật mặt tr&aacute;i sản phẩm, giặt ri&ecirc;ng theo m&agrave;u v&agrave; b&ecirc;n trong t&uacute;i giặt.<br />- N&ecirc;n phơi sản phẩm ở nơi tho&aacute;ng m&aacute;t, tr&aacute;nh &aacute;nh nắng trực tiếp.<br />- N&ecirc;n sấy kh&ocirc; hoặc ủi với nhiệt độ nhỏ hơn 110 độ C.<br />- Lưu &yacute;: Kh&ocirc;ng được ủi c&aacute;c sản phẩm chần g&ograve;n.</p><p>&nbsp;</p>",
        "price": "250000",
        "priceDiscount": "",
        "wareHouse": "100"
    },
    {
        "id": "product10",
        "imgMain": "https://file.hstatic.net/1000280685/collection/1-2_f627c4ff57764d7d8481de4c1fdeda50_medium.jpg",
        "imgHover": "https://product.hstatic.net/1000280685/product/cotton_dysania_xamnhat__19__a9e260b226234eee8bb5847989c08455_large.png",
        "imgDemo": [
            "https://file.hstatic.net/1000280685/collection/1-2_f627c4ff57764d7d8481de4c1fdeda50_medium.jpg",

            "https://product.hstatic.net/1000280685/product/cotton_dysania_xamnhat__19__a9e260b226234eee8bb5847989c08455_large.png"
        ],
        "productName": "PUHA",
        "productDescription": "Topper premium ",
        "description": "<p><strong>M&agrave;u sắc: </strong>Xanh đậu</p><p><strong>K&iacute;ch thước sản phẩm: </strong>D100x R35 cm</p><p><strong>M&ocirc; tả sản phẩm:</strong> Vỏ gối được thiết kế c&oacute; kho&aacute; k&eacute;o dễ th&aacute;o vỏ hoặc lồng ruột gối.&nbsp;</p><p><strong>Chất liệu:&nbsp;</strong>100% Cotton 300 thread count</p><p><strong>Hướng dẫn sử dụng:</strong><br />- Kh&ocirc;ng n&ecirc;n ng&acirc;m sản phẩm.<br />- Kh&ocirc;ng giặt sản phẩm với c&aacute;c loại ho&aacute; chất c&oacute; chất tẩy mạnh.<br />- N&ecirc;n giặt bằng tay/giặt m&aacute;y chế độ nhẹ v&agrave; nhiệt độ b&igrave;nh thường.<br />- N&ecirc;n lật mặt tr&aacute;i sản phẩm, giặt ri&ecirc;ng theo m&agrave;u v&agrave; b&ecirc;n trong t&uacute;i giặt.<br />- N&ecirc;n phơi sản phẩm ở nơi tho&aacute;ng m&aacute;t, tr&aacute;nh &aacute;nh nắng trực tiếp.<br />- N&ecirc;n sấy kh&ocirc; hoặc ủi với nhiệt độ nhỏ hơn 110 độ C.<br />- Lưu &yacute;: Kh&ocirc;ng được ủi c&aacute;c sản phẩm chần g&ograve;n.</p><p>&nbsp;</p>",
        "price": "1190000",
        "priceDiscount": "",
        "wareHouse": "100"
    },
    {
        "id": "product11",
        "imgMain": "https://file.hstatic.net/1000280685/collection/den30do_2d4b9799c2a94e7e9aa96814318809ff_medium.jpg",
        "imgHover": "https://product.hstatic.net/1000280685/product/khungden_1_38bcbb3074aa4f148d90defd03c362bc_large.jpg",
        "imgDemo": [
            "https://file.hstatic.net/1000280685/collection/den30do_2d4b9799c2a94e7e9aa96814318809ff_medium.jpg",

            "https://product.hstatic.net/1000280685/product/khungden_1_38bcbb3074aa4f148d90defd03c362bc_large.jpg"
        ],
        "productName": "ANASTASIA",
        "productDescription": "Sofa băng/góc, đôn rời ",
        "description": "<p><strong>M&agrave;u sắc: </strong>Xanh đậu</p><p><strong>K&iacute;ch thước sản phẩm: </strong>D100x R35 cm</p><p><strong>M&ocirc; tả sản phẩm:</strong> Vỏ gối được thiết kế c&oacute; kho&aacute; k&eacute;o dễ th&aacute;o vỏ hoặc lồng ruột gối.&nbsp;</p><p><strong>Chất liệu:&nbsp;</strong>100% Cotton 300 thread count</p><p><strong>Hướng dẫn sử dụng:</strong><br />- Kh&ocirc;ng n&ecirc;n ng&acirc;m sản phẩm.<br />- Kh&ocirc;ng giặt sản phẩm với c&aacute;c loại ho&aacute; chất c&oacute; chất tẩy mạnh.<br />- N&ecirc;n giặt bằng tay/giặt m&aacute;y chế độ nhẹ v&agrave; nhiệt độ b&igrave;nh thường.<br />- N&ecirc;n lật mặt tr&aacute;i sản phẩm, giặt ri&ecirc;ng theo m&agrave;u v&agrave; b&ecirc;n trong t&uacute;i giặt.<br />- N&ecirc;n phơi sản phẩm ở nơi tho&aacute;ng m&aacute;t, tr&aacute;nh &aacute;nh nắng trực tiếp.<br />- N&ecirc;n sấy kh&ocirc; hoặc ủi với nhiệt độ nhỏ hơn 110 độ C.<br />- Lưu &yacute;: Kh&ocirc;ng được ủi c&aacute;c sản phẩm chần g&ograve;n.</p><p>&nbsp;</p>",
        "price": "9190000",
        "priceDiscount": "",
        "wareHouse": "100"
    },
    {
        "id": "product12",
        "imgMain": "https://file.hstatic.net/1000280685/collection/p6_22ba6aac528c49a5857b5d4d024dc585_medium.png",
        "imgHover": "https://product.hstatic.net/1000280685/product/p6_5cf4037f46674259a809564f1dd20578_a81b7f72d7a6406380fbd8a82f4c51b5_large.png",
        "imgDemo": [
            "https://file.hstatic.net/1000280685/collection/p6_22ba6aac528c49a5857b5d4d024dc585_medium.png",

            "https://product.hstatic.net/1000280685/product/p6_5cf4037f46674259a809564f1dd20578_a81b7f72d7a6406380fbd8a82f4c51b5_large.png"
        ],
        "productName": "ALICE",
        "productDescription": "Sofa băng",
        "description": "<p><strong>M&agrave;u sắc: </strong>Xanh đậu</p><p><strong>K&iacute;ch thước sản phẩm: </strong>D100x R35 cm</p><p><strong>M&ocirc; tả sản phẩm:</strong> Vỏ gối được thiết kế c&oacute; kho&aacute; k&eacute;o dễ th&aacute;o vỏ hoặc lồng ruột gối.&nbsp;</p><p><strong>Chất liệu:&nbsp;</strong>100% Cotton 300 thread count</p><p><strong>Hướng dẫn sử dụng:</strong><br />- Kh&ocirc;ng n&ecirc;n ng&acirc;m sản phẩm.<br />- Kh&ocirc;ng giặt sản phẩm với c&aacute;c loại ho&aacute; chất c&oacute; chất tẩy mạnh.<br />- N&ecirc;n giặt bằng tay/giặt m&aacute;y chế độ nhẹ v&agrave; nhiệt độ b&igrave;nh thường.<br />- N&ecirc;n lật mặt tr&aacute;i sản phẩm, giặt ri&ecirc;ng theo m&agrave;u v&agrave; b&ecirc;n trong t&uacute;i giặt.<br />- N&ecirc;n phơi sản phẩm ở nơi tho&aacute;ng m&aacute;t, tr&aacute;nh &aacute;nh nắng trực tiếp.<br />- N&ecirc;n sấy kh&ocirc; hoặc ủi với nhiệt độ nhỏ hơn 110 độ C.<br />- Lưu &yacute;: Kh&ocirc;ng được ủi c&aacute;c sản phẩm chần g&ograve;n.</p><p>&nbsp;</p>",
        "price": "4590000",
        "priceDiscount": "7590000",
        "wareHouse": "100"
    },
    {
        "id": "product13",
        "imgMain": "https://file.hstatic.net/1000280685/collection/2_16b84acbefe24232a46fbf952a107bbd_medium.jpg",
        "imgHover": "https://product.hstatic.net/1000280685/product/katy_xamnhat_02_60229d0efad44b09b4e78eed23af5714_large.png",
        "imgDemo": [
            "https://file.hstatic.net/1000280685/collection/2_16b84acbefe24232a46fbf952a107bbd_medium.jpg",

            "https://product.hstatic.net/1000280685/product/katy_xamnhat_02_60229d0efad44b09b4e78eed23af5714_large.png"
        ],
        "productName": "JASMIN",
        "productDescription": "Sofa băng",
        "description": "<p><strong>M&agrave;u sắc: </strong>Xanh đậu</p><p><strong>K&iacute;ch thước sản phẩm: </strong>D100x R35 cm</p><p><strong>M&ocirc; tả sản phẩm:</strong> Vỏ gối được thiết kế c&oacute; kho&aacute; k&eacute;o dễ th&aacute;o vỏ hoặc lồng ruột gối.&nbsp;</p><p><strong>Chất liệu:&nbsp;</strong>100% Cotton 300 thread count</p><p><strong>Hướng dẫn sử dụng:</strong><br />- Kh&ocirc;ng n&ecirc;n ng&acirc;m sản phẩm.<br />- Kh&ocirc;ng giặt sản phẩm với c&aacute;c loại ho&aacute; chất c&oacute; chất tẩy mạnh.<br />- N&ecirc;n giặt bằng tay/giặt m&aacute;y chế độ nhẹ v&agrave; nhiệt độ b&igrave;nh thường.<br />- N&ecirc;n lật mặt tr&aacute;i sản phẩm, giặt ri&ecirc;ng theo m&agrave;u v&agrave; b&ecirc;n trong t&uacute;i giặt.<br />- N&ecirc;n phơi sản phẩm ở nơi tho&aacute;ng m&aacute;t, tr&aacute;nh &aacute;nh nắng trực tiếp.<br />- N&ecirc;n sấy kh&ocirc; hoặc ủi với nhiệt độ nhỏ hơn 110 độ C.<br />- Lưu &yacute;: Kh&ocirc;ng được ủi c&aacute;c sản phẩm chần g&ograve;n.</p><p>&nbsp;</p>",
        "price": "10090000",
        "priceDiscount": "14590000",
        "wareHouse": "100"
    },
    {
        "id": "product14",
        "imgMain": "https://file.hstatic.net/1000280685/collection/combo4_2c3f226c8d194979804f74444b5e061e_grande_f8b6dd79863643ed94d68b7cfedd092f_medium.jpg",
        "imgHover": "https://product.hstatic.net/1000280685/product/16__1__large.jpg",
        "imgDemo": [
            "https://file.hstatic.net/1000280685/collection/combo4_2c3f226c8d194979804f74444b5e061e_grande_f8b6dd79863643ed94d68b7cfedd092f_medium.jpg",
            "https://product.hstatic.net/1000280685/product/16__1__large.jpg"
        ],
        "productName": "MOANA",
        "productDescription": "Sofa băng 3 seaters",
        "description": "<p><strong>M&agrave;u sắc: </strong>Xanh đậu</p><p><strong>K&iacute;ch thước sản phẩm: </strong>D100x R35 cm</p><p><strong>M&ocirc; tả sản phẩm:</strong> Vỏ gối được thiết kế c&oacute; kho&aacute; k&eacute;o dễ th&aacute;o vỏ hoặc lồng ruột gối.&nbsp;</p><p><strong>Chất liệu:&nbsp;</strong>100% Cotton 300 thread count</p><p><strong>Hướng dẫn sử dụng:</strong><br />- Kh&ocirc;ng n&ecirc;n ng&acirc;m sản phẩm.<br />- Kh&ocirc;ng giặt sản phẩm với c&aacute;c loại ho&aacute; chất c&oacute; chất tẩy mạnh.<br />- N&ecirc;n giặt bằng tay/giặt m&aacute;y chế độ nhẹ v&agrave; nhiệt độ b&igrave;nh thường.<br />- N&ecirc;n lật mặt tr&aacute;i sản phẩm, giặt ri&ecirc;ng theo m&agrave;u v&agrave; b&ecirc;n trong t&uacute;i giặt.<br />- N&ecirc;n phơi sản phẩm ở nơi tho&aacute;ng m&aacute;t, tr&aacute;nh &aacute;nh nắng trực tiếp.<br />- N&ecirc;n sấy kh&ocirc; hoặc ủi với nhiệt độ nhỏ hơn 110 độ C.<br />- Lưu &yacute;: Kh&ocirc;ng được ủi c&aacute;c sản phẩm chần g&ograve;n.</p><p>&nbsp;</p>",
        "price": "15190000",
        "priceDiscount": "",
        "wareHouse": "100"
    },
    {
        "id": "product15",
        "imgMain": "https://file.hstatic.net/1000280685/collection/file_xavierplus_chanden_matden_b27602820e3d49418f1efec60e4bf30f_grande_57baf13a6c884a819c70a0984808f65d_medium.png",
        "imgHover": "https://product.hstatic.net/1000280685/product/moon-1_large.jpg",
        "imgDemo": [
            "https://file.hstatic.net/1000280685/collection/file_xavierplus_chanden_matden_b27602820e3d49418f1efec60e4bf30f_grande_57baf13a6c884a819c70a0984808f65d_medium.png",
            "https://product.hstatic.net/1000280685/product/moon-1_large.jpg"
        ],
        "productName": "MICHAY",
        "productDescription": "Sofa băng 3 seaters",
        "description": "<p><strong>M&agrave;u sắc: </strong>Xanh đậu</p><p><strong>K&iacute;ch thước sản phẩm: </strong>D100x R35 cm</p><p><strong>M&ocirc; tả sản phẩm:</strong> Vỏ gối được thiết kế c&oacute; kho&aacute; k&eacute;o dễ th&aacute;o vỏ hoặc lồng ruột gối.&nbsp;</p><p><strong>Chất liệu:&nbsp;</strong>100% Cotton 300 thread count</p><p><strong>Hướng dẫn sử dụng:</strong><br />- Kh&ocirc;ng n&ecirc;n ng&acirc;m sản phẩm.<br />- Kh&ocirc;ng giặt sản phẩm với c&aacute;c loại ho&aacute; chất c&oacute; chất tẩy mạnh.<br />- N&ecirc;n giặt bằng tay/giặt m&aacute;y chế độ nhẹ v&agrave; nhiệt độ b&igrave;nh thường.<br />- N&ecirc;n lật mặt tr&aacute;i sản phẩm, giặt ri&ecirc;ng theo m&agrave;u v&agrave; b&ecirc;n trong t&uacute;i giặt.<br />- N&ecirc;n phơi sản phẩm ở nơi tho&aacute;ng m&aacute;t, tr&aacute;nh &aacute;nh nắng trực tiếp.<br />- N&ecirc;n sấy kh&ocirc; hoặc ủi với nhiệt độ nhỏ hơn 110 độ C.<br />- Lưu &yacute;: Kh&ocirc;ng được ủi c&aacute;c sản phẩm chần g&ograve;n.</p><p>&nbsp;</p>",
        "price": "15190000",
        "priceDiscount": "",
        "wareHouse": "100"
    },
    {
        "id": "product16",
        "imgMain": "https://file.hstatic.net/1000280685/collection/ban-goc-den-30-do_1f90a4e9e0f14c26b9def7a7220de6c6_medium.png",
        "imgHover": "https://product.hstatic.net/1000280685/product/xamdam_3_777806e2e95a451f8df359ef6446cf4d_25fe775138b748fbbdcba9f0434e1c1b_large.png",
        "imgDemo": [
            "https://file.hstatic.net/1000280685/collection/ban-goc-den-30-do_1f90a4e9e0f14c26b9def7a7220de6c6_medium.png",

            "https://product.hstatic.net/1000280685/product/xamdam_3_777806e2e95a451f8df359ef6446cf4d_25fe775138b748fbbdcba9f0434e1c1b_large.png"
        ],
        "productName": "MULAN",
        "productDescription": "Sofa bâng 2 seaters",
        "description": "<p><strong>M&agrave;u sắc: </strong>Xanh đậu</p><p><strong>K&iacute;ch thước sản phẩm: </strong>D100x R35 cm</p><p><strong>M&ocirc; tả sản phẩm:</strong> Vỏ gối được thiết kế c&oacute; kho&aacute; k&eacute;o dễ th&aacute;o vỏ hoặc lồng ruột gối.&nbsp;</p><p><strong>Chất liệu:&nbsp;</strong>100% Cotton 300 thread count</p><p><strong>Hướng dẫn sử dụng:</strong><br />- Kh&ocirc;ng n&ecirc;n ng&acirc;m sản phẩm.<br />- Kh&ocirc;ng giặt sản phẩm với c&aacute;c loại ho&aacute; chất c&oacute; chất tẩy mạnh.<br />- N&ecirc;n giặt bằng tay/giặt m&aacute;y chế độ nhẹ v&agrave; nhiệt độ b&igrave;nh thường.<br />- N&ecirc;n lật mặt tr&aacute;i sản phẩm, giặt ri&ecirc;ng theo m&agrave;u v&agrave; b&ecirc;n trong t&uacute;i giặt.<br />- N&ecirc;n phơi sản phẩm ở nơi tho&aacute;ng m&aacute;t, tr&aacute;nh &aacute;nh nắng trực tiếp.<br />- N&ecirc;n sấy kh&ocirc; hoặc ủi với nhiệt độ nhỏ hơn 110 độ C.<br />- Lưu &yacute;: Kh&ocirc;ng được ủi c&aacute;c sản phẩm chần g&ograve;n.</p><p>&nbsp;</p>",
        "price": "15190000",
        "priceDiscount": "",
        "wareHouse": "100"
    },
    {
        "id": "product17",
        "imgMain": "https://file.hstatic.net/1000280685/collection/chin_s__d_244149290f304a1b8b60f4cae8918022_medium.png",
        "imgHover": "https://product.hstatic.net/1000280685/product/ez__15__28665c7f5fbc4b85b2bc39b4c5bdd9a4_large.jpg",
        "imgDemo": [
            "https://file.hstatic.net/1000280685/collection/chin_s__d_244149290f304a1b8b60f4cae8918022_medium.png",

            "https://product.hstatic.net/1000280685/product/ez__15__28665c7f5fbc4b85b2bc39b4c5bdd9a4_large.jpg"
        ],
        "productName": "QUADA",
        "productDescription": "Giường 1m2",
        "description": "<p><strong>M&agrave;u sắc: </strong>Xanh đậu</p><p><strong>K&iacute;ch thước sản phẩm: </strong>D100x R35 cm</p><p><strong>M&ocirc; tả sản phẩm:</strong> Vỏ gối được thiết kế c&oacute; kho&aacute; k&eacute;o dễ th&aacute;o vỏ hoặc lồng ruột gối.&nbsp;</p><p><strong>Chất liệu:&nbsp;</strong>100% Cotton 300 thread count</p><p><strong>Hướng dẫn sử dụng:</strong><br />- Kh&ocirc;ng n&ecirc;n ng&acirc;m sản phẩm.<br />- Kh&ocirc;ng giặt sản phẩm với c&aacute;c loại ho&aacute; chất c&oacute; chất tẩy mạnh.<br />- N&ecirc;n giặt bằng tay/giặt m&aacute;y chế độ nhẹ v&agrave; nhiệt độ b&igrave;nh thường.<br />- N&ecirc;n lật mặt tr&aacute;i sản phẩm, giặt ri&ecirc;ng theo m&agrave;u v&agrave; b&ecirc;n trong t&uacute;i giặt.<br />- N&ecirc;n phơi sản phẩm ở nơi tho&aacute;ng m&aacute;t, tr&aacute;nh &aacute;nh nắng trực tiếp.<br />- N&ecirc;n sấy kh&ocirc; hoặc ủi với nhiệt độ nhỏ hơn 110 độ C.<br />- Lưu &yacute;: Kh&ocirc;ng được ủi c&aacute;c sản phẩm chần g&ograve;n.</p><p>&nbsp;</p>",
        "price": "15190000",
        "priceDiscount": "",
        "wareHouse": "100"
    },
    {
        "id": "product18",
        "imgMain": "https://file.hstatic.net/1000280685/collection/p1_b9a19b1533f94e95b2fbde4393a4e964_medium.png",
        "imgHover": "https://product.hstatic.net/1000280685/product/oli_plus_gotrang__3__3ec3e8812600487788a3585e560c0202_30aeb236122e485e9da4247a648a4f05_large.jpg",
        "imgDemo": [
            "https://file.hstatic.net/1000280685/collection/p1_b9a19b1533f94e95b2fbde4393a4e964_medium.png",

            "https://product.hstatic.net/1000280685/product/oli_plus_gotrang__3__3ec3e8812600487788a3585e560c0202_30aeb236122e485e9da4247a648a4f05_large.jpg"
        ],
        "productName": "JOHY",
        "productDescription": "Giường trắng 1m6",
        "description": "<p><strong>M&agrave;u sắc: </strong>Xanh đậu</p><p><strong>K&iacute;ch thước sản phẩm: </strong>D100x R35 cm</p><p><strong>M&ocirc; tả sản phẩm:</strong> Vỏ gối được thiết kế c&oacute; kho&aacute; k&eacute;o dễ th&aacute;o vỏ hoặc lồng ruột gối.&nbsp;</p><p><strong>Chất liệu:&nbsp;</strong>100% Cotton 300 thread count</p><p><strong>Hướng dẫn sử dụng:</strong><br />- Kh&ocirc;ng n&ecirc;n ng&acirc;m sản phẩm.<br />- Kh&ocirc;ng giặt sản phẩm với c&aacute;c loại ho&aacute; chất c&oacute; chất tẩy mạnh.<br />- N&ecirc;n giặt bằng tay/giặt m&aacute;y chế độ nhẹ v&agrave; nhiệt độ b&igrave;nh thường.<br />- N&ecirc;n lật mặt tr&aacute;i sản phẩm, giặt ri&ecirc;ng theo m&agrave;u v&agrave; b&ecirc;n trong t&uacute;i giặt.<br />- N&ecirc;n phơi sản phẩm ở nơi tho&aacute;ng m&aacute;t, tr&aacute;nh &aacute;nh nắng trực tiếp.<br />- N&ecirc;n sấy kh&ocirc; hoặc ủi với nhiệt độ nhỏ hơn 110 độ C.<br />- Lưu &yacute;: Kh&ocirc;ng được ủi c&aacute;c sản phẩm chần g&ograve;n.</p><p>&nbsp;</p>",
        "price": "15190000",
        "priceDiscount": "",
        "wareHouse": "100"
    },
    {
        "id": "product19",
        "imgMain": "https://file.hstatic.net/1000280685/collection/a_d_1_27bb90719bcd4878b6ce5cbfafcbc5bc_medium.png",
        "imgHover": "https://product.hstatic.net/1000280685/product/go_3_d83ae4858e26429f9b23d6200d8d681c_large.jpg",
        "imgDemo": [
            "https://file.hstatic.net/1000280685/collection/a_d_1_27bb90719bcd4878b6ce5cbfafcbc5bc_medium.png",

            "https://product.hstatic.net/1000280685/product/go_3_d83ae4858e26429f9b23d6200d8d681c_large.jpg"
        ],
        "productName": "LULLABY",
        "productDescription": "Giường 1m8",
        "description": "<p><strong>M&agrave;u sắc: </strong>Xanh đậu</p><p><strong>K&iacute;ch thước sản phẩm: </strong>D100x R35 cm</p><p><strong>M&ocirc; tả sản phẩm:</strong> Vỏ gối được thiết kế c&oacute; kho&aacute; k&eacute;o dễ th&aacute;o vỏ hoặc lồng ruột gối.&nbsp;</p><p><strong>Chất liệu:&nbsp;</strong>100% Cotton 300 thread count</p><p><strong>Hướng dẫn sử dụng:</strong><br />- Kh&ocirc;ng n&ecirc;n ng&acirc;m sản phẩm.<br />- Kh&ocirc;ng giặt sản phẩm với c&aacute;c loại ho&aacute; chất c&oacute; chất tẩy mạnh.<br />- N&ecirc;n giặt bằng tay/giặt m&aacute;y chế độ nhẹ v&agrave; nhiệt độ b&igrave;nh thường.<br />- N&ecirc;n lật mặt tr&aacute;i sản phẩm, giặt ri&ecirc;ng theo m&agrave;u v&agrave; b&ecirc;n trong t&uacute;i giặt.<br />- N&ecirc;n phơi sản phẩm ở nơi tho&aacute;ng m&aacute;t, tr&aacute;nh &aacute;nh nắng trực tiếp.<br />- N&ecirc;n sấy kh&ocirc; hoặc ủi với nhiệt độ nhỏ hơn 110 độ C.<br />- Lưu &yacute;: Kh&ocirc;ng được ủi c&aacute;c sản phẩm chần g&ograve;n.</p><p>&nbsp;</p>",
        "price": "10190000",
        "priceDiscount": "",
        "wareHouse": "100"
    },
    {
        "id": "product20",
        "imgMain": "https://file.hstatic.net/1000280685/collection/coba_hong_2_b495df9036d84fb0b599ffcb05d4e766_medium.png",
        "imgHover": "https://product.hstatic.net/1000280685/product/tencel_magnet_trang_xamnhat__10__d8799c0cf4e84ca8b1fb44aa0e1eb0cd_large.png",
        "imgDemo": [
            "https://file.hstatic.net/1000280685/collection/coba_hong_2_b495df9036d84fb0b599ffcb05d4e766_medium.png",

            "https://product.hstatic.net/1000280685/product/tencel_magnet_trang_xamnhat__10__d8799c0cf4e84ca8b1fb44aa0e1eb0cd_large.png"
        ],
        "productName": "HANO",
        "productDescription": "Giường 1m6",
        "description": "<p><strong>M&agrave;u sắc: </strong>Xanh đậu</p><p><strong>K&iacute;ch thước sản phẩm: </strong>D100x R35 cm</p><p><strong>M&ocirc; tả sản phẩm:</strong> Vỏ gối được thiết kế c&oacute; kho&aacute; k&eacute;o dễ th&aacute;o vỏ hoặc lồng ruột gối.&nbsp;</p><p><strong>Chất liệu:&nbsp;</strong>100% Cotton 300 thread count</p><p><strong>Hướng dẫn sử dụng:</strong><br />- Kh&ocirc;ng n&ecirc;n ng&acirc;m sản phẩm.<br />- Kh&ocirc;ng giặt sản phẩm với c&aacute;c loại ho&aacute; chất c&oacute; chất tẩy mạnh.<br />- N&ecirc;n giặt bằng tay/giặt m&aacute;y chế độ nhẹ v&agrave; nhiệt độ b&igrave;nh thường.<br />- N&ecirc;n lật mặt tr&aacute;i sản phẩm, giặt ri&ecirc;ng theo m&agrave;u v&agrave; b&ecirc;n trong t&uacute;i giặt.<br />- N&ecirc;n phơi sản phẩm ở nơi tho&aacute;ng m&aacute;t, tr&aacute;nh &aacute;nh nắng trực tiếp.<br />- N&ecirc;n sấy kh&ocirc; hoặc ủi với nhiệt độ nhỏ hơn 110 độ C.<br />- Lưu &yacute;: Kh&ocirc;ng được ủi c&aacute;c sản phẩm chần g&ograve;n.</p><p>&nbsp;</p>",
        "price": "12590000",
        "priceDiscount": "",
        "wareHouse": "100"
    },
    {
        "id": "product21",
        "imgMain": "https://file.hstatic.net/1000280685/collection/1-7_dc4c9db64b6e42e6b6626eb15da0d581_medium.png",
        "imgHover": "https://product.hstatic.net/1000280685/product/ez__15__28665c7f5fbc4b85b2bc39b4c5bdd9a4_large.jpg",
        "imgDemo": [
            "https://file.hstatic.net/1000280685/collection/1-7_dc4c9db64b6e42e6b6626eb15da0d581_medium.png",

            "https://product.hstatic.net/1000280685/product/ez__15__28665c7f5fbc4b85b2bc39b4c5bdd9a4_large.jpg"
        ],
        "productName": "HONEY Plus",
        "productDescription": "Bàn ăn, bàn làm việc lớn",
        "description": "<p><strong>M&agrave;u sắc: </strong>Xanh đậu</p><p><strong>K&iacute;ch thước sản phẩm: </strong>D100x R35 cm</p><p><strong>M&ocirc; tả sản phẩm:</strong> Vỏ gối được thiết kế c&oacute; kho&aacute; k&eacute;o dễ th&aacute;o vỏ hoặc lồng ruột gối.&nbsp;</p><p><strong>Chất liệu:&nbsp;</strong>100% Cotton 300 thread count</p><p><strong>Hướng dẫn sử dụng:</strong><br />- Kh&ocirc;ng n&ecirc;n ng&acirc;m sản phẩm.<br />- Kh&ocirc;ng giặt sản phẩm với c&aacute;c loại ho&aacute; chất c&oacute; chất tẩy mạnh.<br />- N&ecirc;n giặt bằng tay/giặt m&aacute;y chế độ nhẹ v&agrave; nhiệt độ b&igrave;nh thường.<br />- N&ecirc;n lật mặt tr&aacute;i sản phẩm, giặt ri&ecirc;ng theo m&agrave;u v&agrave; b&ecirc;n trong t&uacute;i giặt.<br />- N&ecirc;n phơi sản phẩm ở nơi tho&aacute;ng m&aacute;t, tr&aacute;nh &aacute;nh nắng trực tiếp.<br />- N&ecirc;n sấy kh&ocirc; hoặc ủi với nhiệt độ nhỏ hơn 110 độ C.<br />- Lưu &yacute;: Kh&ocirc;ng được ủi c&aacute;c sản phẩm chần g&ograve;n.</p><p>&nbsp;</p>",
        "price": "5190000",
        "priceDiscount": "",
        "wareHouse": "100"
    },
    {
        "id": "product22",
        "imgMain": "https://file.hstatic.net/1000280685/collection/seta_11_b3c8806dd4384251a178fdfbe74e2c1d_medium.jpg",
        "imgHover": "https://product.hstatic.net/1000280685/product/guong-medusa-thucte__6__c527b91078f04734bf003b6568cb22de_large.jpg",
        "imgDemo": [
            "https://file.hstatic.net/1000280685/collection/seta_11_b3c8806dd4384251a178fdfbe74e2c1d_medium.jpg",

            "https://product.hstatic.net/1000280685/product/guong-medusa-thucte__6__c527b91078f04734bf003b6568cb22de_large.jpg"
        ],
        "productName": "HONEY Plus",
        "productDescription": "Bàn ăn, bàn làm việc lớn",
        "description": "<p><strong>M&agrave;u sắc: </strong>Xanh đậu</p><p><strong>K&iacute;ch thước sản phẩm: </strong>D100x R35 cm</p><p><strong>M&ocirc; tả sản phẩm:</strong> Vỏ gối được thiết kế c&oacute; kho&aacute; k&eacute;o dễ th&aacute;o vỏ hoặc lồng ruột gối.&nbsp;</p><p><strong>Chất liệu:&nbsp;</strong>100% Cotton 300 thread count</p><p><strong>Hướng dẫn sử dụng:</strong><br />- Kh&ocirc;ng n&ecirc;n ng&acirc;m sản phẩm.<br />- Kh&ocirc;ng giặt sản phẩm với c&aacute;c loại ho&aacute; chất c&oacute; chất tẩy mạnh.<br />- N&ecirc;n giặt bằng tay/giặt m&aacute;y chế độ nhẹ v&agrave; nhiệt độ b&igrave;nh thường.<br />- N&ecirc;n lật mặt tr&aacute;i sản phẩm, giặt ri&ecirc;ng theo m&agrave;u v&agrave; b&ecirc;n trong t&uacute;i giặt.<br />- N&ecirc;n phơi sản phẩm ở nơi tho&aacute;ng m&aacute;t, tr&aacute;nh &aacute;nh nắng trực tiếp.<br />- N&ecirc;n sấy kh&ocirc; hoặc ủi với nhiệt độ nhỏ hơn 110 độ C.<br />- Lưu &yacute;: Kh&ocirc;ng được ủi c&aacute;c sản phẩm chần g&ograve;n.</p><p>&nbsp;</p>",
        "price": "1190000",
        "priceDiscount": "",
        "wareHouse": "100"
    },
    {
        "id": "product23",
        "imgMain": "https://file.hstatic.net/1000280685/collection/d_2_8221170094a14347bf25759743ece8d7_medium.jpg",
        "imgHover": "https://product.hstatic.net/1000280685/product/guong-mibo-thucte__2__3ea3904acf774296a57ec720fb107018_large.png",
        "imgDemo": [
            "https://file.hstatic.net/1000280685/collection/d_2_8221170094a14347bf25759743ece8d7_medium.jpg",

            "https://product.hstatic.net/1000280685/product/guong-mibo-thucte__2__3ea3904acf774296a57ec720fb107018_large.png"
        ],
        "productName": "SAGO",
        "productDescription": "Bàn ăn",
        "description": "<p><strong>M&agrave;u sắc: </strong>Xanh đậu</p><p><strong>K&iacute;ch thước sản phẩm: </strong>D100x R35 cm</p><p><strong>M&ocirc; tả sản phẩm:</strong> Vỏ gối được thiết kế c&oacute; kho&aacute; k&eacute;o dễ th&aacute;o vỏ hoặc lồng ruột gối.&nbsp;</p><p><strong>Chất liệu:&nbsp;</strong>100% Cotton 300 thread count</p><p><strong>Hướng dẫn sử dụng:</strong><br />- Kh&ocirc;ng n&ecirc;n ng&acirc;m sản phẩm.<br />- Kh&ocirc;ng giặt sản phẩm với c&aacute;c loại ho&aacute; chất c&oacute; chất tẩy mạnh.<br />- N&ecirc;n giặt bằng tay/giặt m&aacute;y chế độ nhẹ v&agrave; nhiệt độ b&igrave;nh thường.<br />- N&ecirc;n lật mặt tr&aacute;i sản phẩm, giặt ri&ecirc;ng theo m&agrave;u v&agrave; b&ecirc;n trong t&uacute;i giặt.<br />- N&ecirc;n phơi sản phẩm ở nơi tho&aacute;ng m&aacute;t, tr&aacute;nh &aacute;nh nắng trực tiếp.<br />- N&ecirc;n sấy kh&ocirc; hoặc ủi với nhiệt độ nhỏ hơn 110 độ C.<br />- Lưu &yacute;: Kh&ocirc;ng được ủi c&aacute;c sản phẩm chần g&ograve;n.</p><p>&nbsp;</p>",
        "price": "4550000",
        "priceDiscount": "",
        "wareHouse": "100"
    },
    {
        "id": "product24",
        "imgMain": "https://file.hstatic.net/1000280685/collection/profile_den_1_chan_6028ad525d5c49f782f103e9a80a66f8_medium.jpg",
        "imgHover": "https://product.hstatic.net/1000280685/product/ez_tuluutru_31_18f45d6d05314829a330db8254ffa5be_large.jpg",
        "imgDemo": [
            "https://file.hstatic.net/1000280685/collection/profile_den_1_chan_6028ad525d5c49f782f103e9a80a66f8_medium.jpg",

            "https://product.hstatic.net/1000280685/product/ez_tuluutru_31_18f45d6d05314829a330db8254ffa5be_large.jpg"
        ],
        "productName": "DALAT",
        "productDescription": "Bàn ăn",
        "description": "<p><strong>M&agrave;u sắc: </strong>Xanh đậu</p><p><strong>K&iacute;ch thước sản phẩm: </strong>D100x R35 cm</p><p><strong>M&ocirc; tả sản phẩm:</strong> Vỏ gối được thiết kế c&oacute; kho&aacute; k&eacute;o dễ th&aacute;o vỏ hoặc lồng ruột gối.&nbsp;</p><p><strong>Chất liệu:&nbsp;</strong>100% Cotton 300 thread count</p><p><strong>Hướng dẫn sử dụng:</strong><br />- Kh&ocirc;ng n&ecirc;n ng&acirc;m sản phẩm.<br />- Kh&ocirc;ng giặt sản phẩm với c&aacute;c loại ho&aacute; chất c&oacute; chất tẩy mạnh.<br />- N&ecirc;n giặt bằng tay/giặt m&aacute;y chế độ nhẹ v&agrave; nhiệt độ b&igrave;nh thường.<br />- N&ecirc;n lật mặt tr&aacute;i sản phẩm, giặt ri&ecirc;ng theo m&agrave;u v&agrave; b&ecirc;n trong t&uacute;i giặt.<br />- N&ecirc;n phơi sản phẩm ở nơi tho&aacute;ng m&aacute;t, tr&aacute;nh &aacute;nh nắng trực tiếp.<br />- N&ecirc;n sấy kh&ocirc; hoặc ủi với nhiệt độ nhỏ hơn 110 độ C.<br />- Lưu &yacute;: Kh&ocirc;ng được ủi c&aacute;c sản phẩm chần g&ograve;n.</p><p>&nbsp;</p>",
        "price": "15190000",
        "priceDiscount": "12590000",
        "wareHouse": "100"
    },
    {
        "id": "product25",
        "imgMain": "https://file.hstatic.net/1000280685/collection/p1_c87b122f8815425bb2c51a7584dd9ab6_medium.png",
        "imgHover": "https://product.hstatic.net/1000280685/product/ez__8__253a52fb9a60493ea43b85e1f5e8ca13_large.jpg",
        "imgDemo": [
            "https://file.hstatic.net/1000280685/collection/p1_c87b122f8815425bb2c51a7584dd9ab6_medium.png",

            "https://product.hstatic.net/1000280685/product/ez__8__253a52fb9a60493ea43b85e1f5e8ca13_large.jpg"
        ],
        "productName": "QLI",
        "productDescription": "Bàn ăn 4-6 người",
        "description": "<p><strong>M&agrave;u sắc: </strong>Xanh đậu</p><p><strong>K&iacute;ch thước sản phẩm: </strong>D100x R35 cm</p><p><strong>M&ocirc; tả sản phẩm:</strong> Vỏ gối được thiết kế c&oacute; kho&aacute; k&eacute;o dễ th&aacute;o vỏ hoặc lồng ruột gối.&nbsp;</p><p><strong>Chất liệu:&nbsp;</strong>100% Cotton 300 thread count</p><p><strong>Hướng dẫn sử dụng:</strong><br />- Kh&ocirc;ng n&ecirc;n ng&acirc;m sản phẩm.<br />- Kh&ocirc;ng giặt sản phẩm với c&aacute;c loại ho&aacute; chất c&oacute; chất tẩy mạnh.<br />- N&ecirc;n giặt bằng tay/giặt m&aacute;y chế độ nhẹ v&agrave; nhiệt độ b&igrave;nh thường.<br />- N&ecirc;n lật mặt tr&aacute;i sản phẩm, giặt ri&ecirc;ng theo m&agrave;u v&agrave; b&ecirc;n trong t&uacute;i giặt.<br />- N&ecirc;n phơi sản phẩm ở nơi tho&aacute;ng m&aacute;t, tr&aacute;nh &aacute;nh nắng trực tiếp.<br />- N&ecirc;n sấy kh&ocirc; hoặc ủi với nhiệt độ nhỏ hơn 110 độ C.<br />- Lưu &yacute;: Kh&ocirc;ng được ủi c&aacute;c sản phẩm chần g&ograve;n.</p><p>&nbsp;</p>",
        "price": "5790000",
        "priceDiscount": "",
        "wareHouse": "100"
    },
    {
        "id": "product26",
        "imgMain": "https://file.hstatic.net/1000280685/collection/2_6dc4cd1d4bcb47e4ae2bbf2ab2f8ed25_medium.jpg",
        "imgHover": "https://product.hstatic.net/1000280685/product/ez__15__28665c7f5fbc4b85b2bc39b4c5bdd9a4_large.jpg",
        "imgDemo": [
            "https://file.hstatic.net/1000280685/collection/2_6dc4cd1d4bcb47e4ae2bbf2ab2f8ed25_medium.jpg",

            "https://product.hstatic.net/1000280685/product/ez__15__28665c7f5fbc4b85b2bc39b4c5bdd9a4_large.jpg"
        ],
        "productName": "COTTON DYSANIA",
        "productDescription": "Combo 5 món",
        "description": "<p><strong>M&agrave;u sắc: </strong>Xanh đậu</p><p><strong>K&iacute;ch thước sản phẩm: </strong>D100x R35 cm</p><p><strong>M&ocirc; tả sản phẩm:</strong> Vỏ gối được thiết kế c&oacute; kho&aacute; k&eacute;o dễ th&aacute;o vỏ hoặc lồng ruột gối.&nbsp;</p><p><strong>Chất liệu:&nbsp;</strong>100% Cotton 300 thread count</p><p><strong>Hướng dẫn sử dụng:</strong><br />- Kh&ocirc;ng n&ecirc;n ng&acirc;m sản phẩm.<br />- Kh&ocirc;ng giặt sản phẩm với c&aacute;c loại ho&aacute; chất c&oacute; chất tẩy mạnh.<br />- N&ecirc;n giặt bằng tay/giặt m&aacute;y chế độ nhẹ v&agrave; nhiệt độ b&igrave;nh thường.<br />- N&ecirc;n lật mặt tr&aacute;i sản phẩm, giặt ri&ecirc;ng theo m&agrave;u v&agrave; b&ecirc;n trong t&uacute;i giặt.<br />- N&ecirc;n phơi sản phẩm ở nơi tho&aacute;ng m&aacute;t, tr&aacute;nh &aacute;nh nắng trực tiếp.<br />- N&ecirc;n sấy kh&ocirc; hoặc ủi với nhiệt độ nhỏ hơn 110 độ C.<br />- Lưu &yacute;: Kh&ocirc;ng được ủi c&aacute;c sản phẩm chần g&ograve;n.</p><p>&nbsp;</p>",
        "price": "1690000",
        "priceDiscount": "5590000",
        "wareHouse": "100"
    },
    {
        "id": "product27",
        "imgMain": "https://file.hstatic.net/1000280685/collection/a011_01_98adf64f2d57418fa681c6ab8b0c5f39_medium.jpg",
        "imgHover": "https://product.hstatic.net/1000280685/product/chin_trang__4__90cfc2c999c3437b8f0f87a127c57c90_large.png",
        "imgDemo": [
            "https://file.hstatic.net/1000280685/collection/a011_01_98adf64f2d57418fa681c6ab8b0c5f39_medium.jpg",

            "https://product.hstatic.net/1000280685/product/chin_trang__4__90cfc2c999c3437b8f0f87a127c57c90_large.png"
        ],
        "productName": "ALUS",
        "productDescription": "Ruột gối ôm chữ nhật premium",
        "description": "<p><strong>M&agrave;u sắc: </strong>Xanh đậu</p><p><strong>K&iacute;ch thước sản phẩm: </strong>D100x R35 cm</p><p><strong>M&ocirc; tả sản phẩm:</strong> Vỏ gối được thiết kế c&oacute; kho&aacute; k&eacute;o dễ th&aacute;o vỏ hoặc lồng ruột gối.&nbsp;</p><p><strong>Chất liệu:&nbsp;</strong>100% Cotton 300 thread count</p><p><strong>Hướng dẫn sử dụng:</strong><br />- Kh&ocirc;ng n&ecirc;n ng&acirc;m sản phẩm.<br />- Kh&ocirc;ng giặt sản phẩm với c&aacute;c loại ho&aacute; chất c&oacute; chất tẩy mạnh.<br />- N&ecirc;n giặt bằng tay/giặt m&aacute;y chế độ nhẹ v&agrave; nhiệt độ b&igrave;nh thường.<br />- N&ecirc;n lật mặt tr&aacute;i sản phẩm, giặt ri&ecirc;ng theo m&agrave;u v&agrave; b&ecirc;n trong t&uacute;i giặt.<br />- N&ecirc;n phơi sản phẩm ở nơi tho&aacute;ng m&aacute;t, tr&aacute;nh &aacute;nh nắng trực tiếp.<br />- N&ecirc;n sấy kh&ocirc; hoặc ủi với nhiệt độ nhỏ hơn 110 độ C.<br />- Lưu &yacute;: Kh&ocirc;ng được ủi c&aacute;c sản phẩm chần g&ograve;n.</p><p>&nbsp;</p>",
        "price": "190000",
        "priceDiscount": "590000",
        "wareHouse": "100"
    },
    {
        "id": "product28",
        "imgMain": "https://file.hstatic.net/1000280685/collection/p1-6_07d8ffe29dad4df4b67d47357be33d45_medium.png",
        "imgHover": "https://product.hstatic.net/1000280685/product/cotton_dysania_xamnhat__19__a9e260b226234eee8bb5847989c08455_large.png",
        "imgDemo": [
            "https://file.hstatic.net/1000280685/collection/p1-6_07d8ffe29dad4df4b67d47357be33d45_medium.png",

            "https://product.hstatic.net/1000280685/product/cotton_dysania_xamnhat__19__a9e260b226234eee8bb5847989c08455_large.png"
        ],
        "productName": "DOUX",
        "productDescription": "Ruột gối nằm standard",
        "description": "<p><strong>M&agrave;u sắc: </strong>Xanh đậu</p><p><strong>K&iacute;ch thước sản phẩm: </strong>D100x R35 cm</p><p><strong>M&ocirc; tả sản phẩm:</strong> Vỏ gối được thiết kế c&oacute; kho&aacute; k&eacute;o dễ th&aacute;o vỏ hoặc lồng ruột gối.&nbsp;</p><p><strong>Chất liệu:&nbsp;</strong>100% Cotton 300 thread count</p><p><strong>Hướng dẫn sử dụng:</strong><br />- Kh&ocirc;ng n&ecirc;n ng&acirc;m sản phẩm.<br />- Kh&ocirc;ng giặt sản phẩm với c&aacute;c loại ho&aacute; chất c&oacute; chất tẩy mạnh.<br />- N&ecirc;n giặt bằng tay/giặt m&aacute;y chế độ nhẹ v&agrave; nhiệt độ b&igrave;nh thường.<br />- N&ecirc;n lật mặt tr&aacute;i sản phẩm, giặt ri&ecirc;ng theo m&agrave;u v&agrave; b&ecirc;n trong t&uacute;i giặt.<br />- N&ecirc;n phơi sản phẩm ở nơi tho&aacute;ng m&aacute;t, tr&aacute;nh &aacute;nh nắng trực tiếp.<br />- N&ecirc;n sấy kh&ocirc; hoặc ủi với nhiệt độ nhỏ hơn 110 độ C.<br />- Lưu &yacute;: Kh&ocirc;ng được ủi c&aacute;c sản phẩm chần g&ograve;n.</p><p>&nbsp;</p>",
        "price": "90000",
        "priceDiscount": "",
        "wareHouse": "100"
    },
    {
        "id": "product29",
        "imgMain": "https://file.hstatic.net/1000280685/collection/profile-gio-do-black_d9ad3eb32365469688c6244364329f08_large_72e91275f967463294cb216e82db3c2d_medium.png",
        "imgHover": "https://product.hstatic.net/1000280685/product/xam_3_d088178cc53e49899a558d11a0c79b18_3768eadc53014f14b16b11ae1a96fc0c_large.jpg",
        "imgDemo": [
            "https://file.hstatic.net/1000280685/collection/profile-gio-do-black_d9ad3eb32365469688c6244364329f08_large_72e91275f967463294cb216e82db3c2d_medium.png",
            "https://product.hstatic.net/1000280685/product/xam_3_d088178cc53e49899a558d11a0c79b18_3768eadc53014f14b16b11ae1a96fc0c_large.jpg"
        ],
        "productName": "MOLA",
        "productDescription": "Ruột chăn standard ",
        "description": "<p><strong>M&agrave;u sắc: </strong>Xanh đậu</p><p><strong>K&iacute;ch thước sản phẩm: </strong>D100x R35 cm</p><p><strong>M&ocirc; tả sản phẩm:</strong> Vỏ gối được thiết kế c&oacute; kho&aacute; k&eacute;o dễ th&aacute;o vỏ hoặc lồng ruột gối.&nbsp;</p><p><strong>Chất liệu:&nbsp;</strong>100% Cotton 300 thread count</p><p><strong>Hướng dẫn sử dụng:</strong><br />- Kh&ocirc;ng n&ecirc;n ng&acirc;m sản phẩm.<br />- Kh&ocirc;ng giặt sản phẩm với c&aacute;c loại ho&aacute; chất c&oacute; chất tẩy mạnh.<br />- N&ecirc;n giặt bằng tay/giặt m&aacute;y chế độ nhẹ v&agrave; nhiệt độ b&igrave;nh thường.<br />- N&ecirc;n lật mặt tr&aacute;i sản phẩm, giặt ri&ecirc;ng theo m&agrave;u v&agrave; b&ecirc;n trong t&uacute;i giặt.<br />- N&ecirc;n phơi sản phẩm ở nơi tho&aacute;ng m&aacute;t, tr&aacute;nh &aacute;nh nắng trực tiếp.<br />- N&ecirc;n sấy kh&ocirc; hoặc ủi với nhiệt độ nhỏ hơn 110 độ C.<br />- Lưu &yacute;: Kh&ocirc;ng được ủi c&aacute;c sản phẩm chần g&ograve;n.</p><p>&nbsp;</p>",
        "price": "250000",
        "priceDiscount": "",
        "wareHouse": "100"
    },
    {
        "id": "product30",
        "imgMain": "https://file.hstatic.net/1000280685/collection/1-2_f627c4ff57764d7d8481de4c1fdeda50_medium.jpg",
        "imgHover": "https://product.hstatic.net/1000280685/product/cotton_dysania_xamnhat__19__a9e260b226234eee8bb5847989c08455_large.png",
        "imgDemo": [
            "https://file.hstatic.net/1000280685/collection/1-2_f627c4ff57764d7d8481de4c1fdeda50_medium.jpg",

            "https://product.hstatic.net/1000280685/product/cotton_dysania_xamnhat__19__a9e260b226234eee8bb5847989c08455_large.png"
        ],
        "productName": "PUHA",
        "productDescription": "Topper premium ",
        "description": "<p><strong>M&agrave;u sắc: </strong>Xanh đậu</p><p><strong>K&iacute;ch thước sản phẩm: </strong>D100x R35 cm</p><p><strong>M&ocirc; tả sản phẩm:</strong> Vỏ gối được thiết kế c&oacute; kho&aacute; k&eacute;o dễ th&aacute;o vỏ hoặc lồng ruột gối.&nbsp;</p><p><strong>Chất liệu:&nbsp;</strong>100% Cotton 300 thread count</p><p><strong>Hướng dẫn sử dụng:</strong><br />- Kh&ocirc;ng n&ecirc;n ng&acirc;m sản phẩm.<br />- Kh&ocirc;ng giặt sản phẩm với c&aacute;c loại ho&aacute; chất c&oacute; chất tẩy mạnh.<br />- N&ecirc;n giặt bằng tay/giặt m&aacute;y chế độ nhẹ v&agrave; nhiệt độ b&igrave;nh thường.<br />- N&ecirc;n lật mặt tr&aacute;i sản phẩm, giặt ri&ecirc;ng theo m&agrave;u v&agrave; b&ecirc;n trong t&uacute;i giặt.<br />- N&ecirc;n phơi sản phẩm ở nơi tho&aacute;ng m&aacute;t, tr&aacute;nh &aacute;nh nắng trực tiếp.<br />- N&ecirc;n sấy kh&ocirc; hoặc ủi với nhiệt độ nhỏ hơn 110 độ C.<br />- Lưu &yacute;: Kh&ocirc;ng được ủi c&aacute;c sản phẩm chần g&ograve;n.</p><p>&nbsp;</p>",
        "price": "1190000",
        "priceDiscount": "",
        "wareHouse": "100"
    },
    {
        "id": "product31",
        "imgMain": "https://file.hstatic.net/1000280685/collection/den30do_2d4b9799c2a94e7e9aa96814318809ff_medium.jpg",
        "imgHover": "https://product.hstatic.net/1000280685/product/khungden_1_38bcbb3074aa4f148d90defd03c362bc_large.jpg",
        "imgDemo": [
            "https://file.hstatic.net/1000280685/collection/den30do_2d4b9799c2a94e7e9aa96814318809ff_medium.jpg",

            "https://product.hstatic.net/1000280685/product/khungden_1_38bcbb3074aa4f148d90defd03c362bc_large.jpg"
        ],
        "productName": "ANASTASIA",
        "productDescription": "Sofa băng/góc, đôn rời ",
        "description": "<p><strong>M&agrave;u sắc: </strong>Xanh đậu</p><p><strong>K&iacute;ch thước sản phẩm: </strong>D100x R35 cm</p><p><strong>M&ocirc; tả sản phẩm:</strong> Vỏ gối được thiết kế c&oacute; kho&aacute; k&eacute;o dễ th&aacute;o vỏ hoặc lồng ruột gối.&nbsp;</p><p><strong>Chất liệu:&nbsp;</strong>100% Cotton 300 thread count</p><p><strong>Hướng dẫn sử dụng:</strong><br />- Kh&ocirc;ng n&ecirc;n ng&acirc;m sản phẩm.<br />- Kh&ocirc;ng giặt sản phẩm với c&aacute;c loại ho&aacute; chất c&oacute; chất tẩy mạnh.<br />- N&ecirc;n giặt bằng tay/giặt m&aacute;y chế độ nhẹ v&agrave; nhiệt độ b&igrave;nh thường.<br />- N&ecirc;n lật mặt tr&aacute;i sản phẩm, giặt ri&ecirc;ng theo m&agrave;u v&agrave; b&ecirc;n trong t&uacute;i giặt.<br />- N&ecirc;n phơi sản phẩm ở nơi tho&aacute;ng m&aacute;t, tr&aacute;nh &aacute;nh nắng trực tiếp.<br />- N&ecirc;n sấy kh&ocirc; hoặc ủi với nhiệt độ nhỏ hơn 110 độ C.<br />- Lưu &yacute;: Kh&ocirc;ng được ủi c&aacute;c sản phẩm chần g&ograve;n.</p><p>&nbsp;</p>",
        "price": "9190000",
        "priceDiscount": "",
        "wareHouse": "100"
    },
    {
        "id": "product32",
        "imgMain": "https://file.hstatic.net/1000280685/collection/p6_22ba6aac528c49a5857b5d4d024dc585_medium.png",
        "imgHover": "https://product.hstatic.net/1000280685/product/p6_5cf4037f46674259a809564f1dd20578_a81b7f72d7a6406380fbd8a82f4c51b5_large.png",
        "imgDemo": [
            "https://file.hstatic.net/1000280685/collection/p6_22ba6aac528c49a5857b5d4d024dc585_medium.png",

            "https://product.hstatic.net/1000280685/product/p6_5cf4037f46674259a809564f1dd20578_a81b7f72d7a6406380fbd8a82f4c51b5_large.png"
        ],
        "productName": "ALICE",
        "productDescription": "Sofa băng",
        "description": "<p><strong>M&agrave;u sắc: </strong>Xanh đậu</p><p><strong>K&iacute;ch thước sản phẩm: </strong>D100x R35 cm</p><p><strong>M&ocirc; tả sản phẩm:</strong> Vỏ gối được thiết kế c&oacute; kho&aacute; k&eacute;o dễ th&aacute;o vỏ hoặc lồng ruột gối.&nbsp;</p><p><strong>Chất liệu:&nbsp;</strong>100% Cotton 300 thread count</p><p><strong>Hướng dẫn sử dụng:</strong><br />- Kh&ocirc;ng n&ecirc;n ng&acirc;m sản phẩm.<br />- Kh&ocirc;ng giặt sản phẩm với c&aacute;c loại ho&aacute; chất c&oacute; chất tẩy mạnh.<br />- N&ecirc;n giặt bằng tay/giặt m&aacute;y chế độ nhẹ v&agrave; nhiệt độ b&igrave;nh thường.<br />- N&ecirc;n lật mặt tr&aacute;i sản phẩm, giặt ri&ecirc;ng theo m&agrave;u v&agrave; b&ecirc;n trong t&uacute;i giặt.<br />- N&ecirc;n phơi sản phẩm ở nơi tho&aacute;ng m&aacute;t, tr&aacute;nh &aacute;nh nắng trực tiếp.<br />- N&ecirc;n sấy kh&ocirc; hoặc ủi với nhiệt độ nhỏ hơn 110 độ C.<br />- Lưu &yacute;: Kh&ocirc;ng được ủi c&aacute;c sản phẩm chần g&ograve;n.</p><p>&nbsp;</p>",
        "price": "4590000",
        "priceDiscount": "7590000",
        "wareHouse": "100"
    },
    {
        "id": "product33",
        "imgMain": "https://file.hstatic.net/1000280685/collection/2_16b84acbefe24232a46fbf952a107bbd_medium.jpg",
        "imgHover": "https://product.hstatic.net/1000280685/product/katy_xamnhat_02_60229d0efad44b09b4e78eed23af5714_large.png",
        "imgDemo": [
            "https://file.hstatic.net/1000280685/collection/2_16b84acbefe24232a46fbf952a107bbd_medium.jpg",

            "https://product.hstatic.net/1000280685/product/katy_xamnhat_02_60229d0efad44b09b4e78eed23af5714_large.png"
        ],
        "productName": "JASMIN",
        "productDescription": "Sofa băng",
        "description": "<p><strong>M&agrave;u sắc: </strong>Xanh đậu</p><p><strong>K&iacute;ch thước sản phẩm: </strong>D100x R35 cm</p><p><strong>M&ocirc; tả sản phẩm:</strong> Vỏ gối được thiết kế c&oacute; kho&aacute; k&eacute;o dễ th&aacute;o vỏ hoặc lồng ruột gối.&nbsp;</p><p><strong>Chất liệu:&nbsp;</strong>100% Cotton 300 thread count</p><p><strong>Hướng dẫn sử dụng:</strong><br />- Kh&ocirc;ng n&ecirc;n ng&acirc;m sản phẩm.<br />- Kh&ocirc;ng giặt sản phẩm với c&aacute;c loại ho&aacute; chất c&oacute; chất tẩy mạnh.<br />- N&ecirc;n giặt bằng tay/giặt m&aacute;y chế độ nhẹ v&agrave; nhiệt độ b&igrave;nh thường.<br />- N&ecirc;n lật mặt tr&aacute;i sản phẩm, giặt ri&ecirc;ng theo m&agrave;u v&agrave; b&ecirc;n trong t&uacute;i giặt.<br />- N&ecirc;n phơi sản phẩm ở nơi tho&aacute;ng m&aacute;t, tr&aacute;nh &aacute;nh nắng trực tiếp.<br />- N&ecirc;n sấy kh&ocirc; hoặc ủi với nhiệt độ nhỏ hơn 110 độ C.<br />- Lưu &yacute;: Kh&ocirc;ng được ủi c&aacute;c sản phẩm chần g&ograve;n.</p><p>&nbsp;</p>",
        "price": "10090000",
        "priceDiscount": "14590000",
        "wareHouse": "100"
    },
    {
        "id": "product34",
        "imgMain": "https://file.hstatic.net/1000280685/collection/combo4_2c3f226c8d194979804f74444b5e061e_grande_f8b6dd79863643ed94d68b7cfedd092f_medium.jpg",
        "imgHover": "https://product.hstatic.net/1000280685/product/16__1__large.jpg",
        "imgDemo": [
            "https://file.hstatic.net/1000280685/collection/combo4_2c3f226c8d194979804f74444b5e061e_grande_f8b6dd79863643ed94d68b7cfedd092f_medium.jpg",
            "https://product.hstatic.net/1000280685/product/16__1__large.jpg"
        ],
        "productName": "MOANA",
        "productDescription": "Sofa băng 3 seaters",
        "description": "<p><strong>M&agrave;u sắc: </strong>Xanh đậu</p><p><strong>K&iacute;ch thước sản phẩm: </strong>D100x R35 cm</p><p><strong>M&ocirc; tả sản phẩm:</strong> Vỏ gối được thiết kế c&oacute; kho&aacute; k&eacute;o dễ th&aacute;o vỏ hoặc lồng ruột gối.&nbsp;</p><p><strong>Chất liệu:&nbsp;</strong>100% Cotton 300 thread count</p><p><strong>Hướng dẫn sử dụng:</strong><br />- Kh&ocirc;ng n&ecirc;n ng&acirc;m sản phẩm.<br />- Kh&ocirc;ng giặt sản phẩm với c&aacute;c loại ho&aacute; chất c&oacute; chất tẩy mạnh.<br />- N&ecirc;n giặt bằng tay/giặt m&aacute;y chế độ nhẹ v&agrave; nhiệt độ b&igrave;nh thường.<br />- N&ecirc;n lật mặt tr&aacute;i sản phẩm, giặt ri&ecirc;ng theo m&agrave;u v&agrave; b&ecirc;n trong t&uacute;i giặt.<br />- N&ecirc;n phơi sản phẩm ở nơi tho&aacute;ng m&aacute;t, tr&aacute;nh &aacute;nh nắng trực tiếp.<br />- N&ecirc;n sấy kh&ocirc; hoặc ủi với nhiệt độ nhỏ hơn 110 độ C.<br />- Lưu &yacute;: Kh&ocirc;ng được ủi c&aacute;c sản phẩm chần g&ograve;n.</p><p>&nbsp;</p>",
        "price": "15190000",
        "priceDiscount": "",
        "wareHouse": "100"
    },
    {
        "id": "product35",
        "imgMain": "https://file.hstatic.net/1000280685/collection/file_xavierplus_chanden_matden_b27602820e3d49418f1efec60e4bf30f_grande_57baf13a6c884a819c70a0984808f65d_medium.png",
        "imgHover": "https://product.hstatic.net/1000280685/product/moon-1_large.jpg",
        "imgDemo": [
            "https://file.hstatic.net/1000280685/collection/file_xavierplus_chanden_matden_b27602820e3d49418f1efec60e4bf30f_grande_57baf13a6c884a819c70a0984808f65d_medium.png",
            "https://product.hstatic.net/1000280685/product/moon-1_large.jpg"
        ],
        "productName": "MICHAY",
        "productDescription": "Sofa băng 3 seaters",
        "description": "<p><strong>M&agrave;u sắc: </strong>Xanh đậu</p><p><strong>K&iacute;ch thước sản phẩm: </strong>D100x R35 cm</p><p><strong>M&ocirc; tả sản phẩm:</strong> Vỏ gối được thiết kế c&oacute; kho&aacute; k&eacute;o dễ th&aacute;o vỏ hoặc lồng ruột gối.&nbsp;</p><p><strong>Chất liệu:&nbsp;</strong>100% Cotton 300 thread count</p><p><strong>Hướng dẫn sử dụng:</strong><br />- Kh&ocirc;ng n&ecirc;n ng&acirc;m sản phẩm.<br />- Kh&ocirc;ng giặt sản phẩm với c&aacute;c loại ho&aacute; chất c&oacute; chất tẩy mạnh.<br />- N&ecirc;n giặt bằng tay/giặt m&aacute;y chế độ nhẹ v&agrave; nhiệt độ b&igrave;nh thường.<br />- N&ecirc;n lật mặt tr&aacute;i sản phẩm, giặt ri&ecirc;ng theo m&agrave;u v&agrave; b&ecirc;n trong t&uacute;i giặt.<br />- N&ecirc;n phơi sản phẩm ở nơi tho&aacute;ng m&aacute;t, tr&aacute;nh &aacute;nh nắng trực tiếp.<br />- N&ecirc;n sấy kh&ocirc; hoặc ủi với nhiệt độ nhỏ hơn 110 độ C.<br />- Lưu &yacute;: Kh&ocirc;ng được ủi c&aacute;c sản phẩm chần g&ograve;n.</p><p>&nbsp;</p>",
        "price": "15190000",
        "priceDiscount": "",
        "wareHouse": "100"
    },
    {
        "id": "product36",
        "imgMain": "https://file.hstatic.net/1000280685/collection/ban-goc-den-30-do_1f90a4e9e0f14c26b9def7a7220de6c6_medium.png",
        "imgHover": "https://product.hstatic.net/1000280685/product/xamdam_3_777806e2e95a451f8df359ef6446cf4d_25fe775138b748fbbdcba9f0434e1c1b_large.png",
        "imgDemo": [
            "https://file.hstatic.net/1000280685/collection/ban-goc-den-30-do_1f90a4e9e0f14c26b9def7a7220de6c6_medium.png",

            "https://product.hstatic.net/1000280685/product/xamdam_3_777806e2e95a451f8df359ef6446cf4d_25fe775138b748fbbdcba9f0434e1c1b_large.png"
        ],
        "productName": "MULAN",
        "productDescription": "Sofa bâng 2 seaters",
        "description": "<p><strong>M&agrave;u sắc: </strong>Xanh đậu</p><p><strong>K&iacute;ch thước sản phẩm: </strong>D100x R35 cm</p><p><strong>M&ocirc; tả sản phẩm:</strong> Vỏ gối được thiết kế c&oacute; kho&aacute; k&eacute;o dễ th&aacute;o vỏ hoặc lồng ruột gối.&nbsp;</p><p><strong>Chất liệu:&nbsp;</strong>100% Cotton 300 thread count</p><p><strong>Hướng dẫn sử dụng:</strong><br />- Kh&ocirc;ng n&ecirc;n ng&acirc;m sản phẩm.<br />- Kh&ocirc;ng giặt sản phẩm với c&aacute;c loại ho&aacute; chất c&oacute; chất tẩy mạnh.<br />- N&ecirc;n giặt bằng tay/giặt m&aacute;y chế độ nhẹ v&agrave; nhiệt độ b&igrave;nh thường.<br />- N&ecirc;n lật mặt tr&aacute;i sản phẩm, giặt ri&ecirc;ng theo m&agrave;u v&agrave; b&ecirc;n trong t&uacute;i giặt.<br />- N&ecirc;n phơi sản phẩm ở nơi tho&aacute;ng m&aacute;t, tr&aacute;nh &aacute;nh nắng trực tiếp.<br />- N&ecirc;n sấy kh&ocirc; hoặc ủi với nhiệt độ nhỏ hơn 110 độ C.<br />- Lưu &yacute;: Kh&ocirc;ng được ủi c&aacute;c sản phẩm chần g&ograve;n.</p><p>&nbsp;</p>",
        "price": "15190000",
        "priceDiscount": "",
        "wareHouse": "100"
    },
    {
        "id": "product37",
        "imgMain": "https://file.hstatic.net/1000280685/collection/chin_s__d_244149290f304a1b8b60f4cae8918022_medium.png",
        "imgHover": "https://product.hstatic.net/1000280685/product/ez__15__28665c7f5fbc4b85b2bc39b4c5bdd9a4_large.jpg",
        "imgDemo": [
            "https://file.hstatic.net/1000280685/collection/chin_s__d_244149290f304a1b8b60f4cae8918022_medium.png",

            "https://product.hstatic.net/1000280685/product/ez__15__28665c7f5fbc4b85b2bc39b4c5bdd9a4_large.jpg"
        ],
        "productName": "QUADA",
        "productDescription": "Giường 1m2",
        "description": "<p><strong>M&agrave;u sắc: </strong>Xanh đậu</p><p><strong>K&iacute;ch thước sản phẩm: </strong>D100x R35 cm</p><p><strong>M&ocirc; tả sản phẩm:</strong> Vỏ gối được thiết kế c&oacute; kho&aacute; k&eacute;o dễ th&aacute;o vỏ hoặc lồng ruột gối.&nbsp;</p><p><strong>Chất liệu:&nbsp;</strong>100% Cotton 300 thread count</p><p><strong>Hướng dẫn sử dụng:</strong><br />- Kh&ocirc;ng n&ecirc;n ng&acirc;m sản phẩm.<br />- Kh&ocirc;ng giặt sản phẩm với c&aacute;c loại ho&aacute; chất c&oacute; chất tẩy mạnh.<br />- N&ecirc;n giặt bằng tay/giặt m&aacute;y chế độ nhẹ v&agrave; nhiệt độ b&igrave;nh thường.<br />- N&ecirc;n lật mặt tr&aacute;i sản phẩm, giặt ri&ecirc;ng theo m&agrave;u v&agrave; b&ecirc;n trong t&uacute;i giặt.<br />- N&ecirc;n phơi sản phẩm ở nơi tho&aacute;ng m&aacute;t, tr&aacute;nh &aacute;nh nắng trực tiếp.<br />- N&ecirc;n sấy kh&ocirc; hoặc ủi với nhiệt độ nhỏ hơn 110 độ C.<br />- Lưu &yacute;: Kh&ocirc;ng được ủi c&aacute;c sản phẩm chần g&ograve;n.</p><p>&nbsp;</p>",
        "price": "15190000",
        "priceDiscount": "",
        "wareHouse": "100"
    },
    {
        "id": "product38",
        "imgMain": "https://file.hstatic.net/1000280685/collection/p1_b9a19b1533f94e95b2fbde4393a4e964_medium.png",
        "imgHover": "https://product.hstatic.net/1000280685/product/oli_plus_gotrang__3__3ec3e8812600487788a3585e560c0202_30aeb236122e485e9da4247a648a4f05_large.jpg",
        "imgDemo": [
            "https://file.hstatic.net/1000280685/collection/p1_b9a19b1533f94e95b2fbde4393a4e964_medium.png",

            "https://product.hstatic.net/1000280685/product/oli_plus_gotrang__3__3ec3e8812600487788a3585e560c0202_30aeb236122e485e9da4247a648a4f05_large.jpg"
        ],
        "productName": "JOHY",
        "productDescription": "Giường trắng 1m6",
        "description": "<p><strong>M&agrave;u sắc: </strong>Xanh đậu</p><p><strong>K&iacute;ch thước sản phẩm: </strong>D100x R35 cm</p><p><strong>M&ocirc; tả sản phẩm:</strong> Vỏ gối được thiết kế c&oacute; kho&aacute; k&eacute;o dễ th&aacute;o vỏ hoặc lồng ruột gối.&nbsp;</p><p><strong>Chất liệu:&nbsp;</strong>100% Cotton 300 thread count</p><p><strong>Hướng dẫn sử dụng:</strong><br />- Kh&ocirc;ng n&ecirc;n ng&acirc;m sản phẩm.<br />- Kh&ocirc;ng giặt sản phẩm với c&aacute;c loại ho&aacute; chất c&oacute; chất tẩy mạnh.<br />- N&ecirc;n giặt bằng tay/giặt m&aacute;y chế độ nhẹ v&agrave; nhiệt độ b&igrave;nh thường.<br />- N&ecirc;n lật mặt tr&aacute;i sản phẩm, giặt ri&ecirc;ng theo m&agrave;u v&agrave; b&ecirc;n trong t&uacute;i giặt.<br />- N&ecirc;n phơi sản phẩm ở nơi tho&aacute;ng m&aacute;t, tr&aacute;nh &aacute;nh nắng trực tiếp.<br />- N&ecirc;n sấy kh&ocirc; hoặc ủi với nhiệt độ nhỏ hơn 110 độ C.<br />- Lưu &yacute;: Kh&ocirc;ng được ủi c&aacute;c sản phẩm chần g&ograve;n.</p><p>&nbsp;</p>",
        "price": "15190000",
        "priceDiscount": "",
        "wareHouse": "100"
    },
    {
        "id": "product39",
        "imgMain": "https://file.hstatic.net/1000280685/collection/a_d_1_27bb90719bcd4878b6ce5cbfafcbc5bc_medium.png",
        "imgHover": "https://product.hstatic.net/1000280685/product/go_3_d83ae4858e26429f9b23d6200d8d681c_large.jpg",
        "imgDemo": [
            "https://file.hstatic.net/1000280685/collection/a_d_1_27bb90719bcd4878b6ce5cbfafcbc5bc_medium.png",

            "https://product.hstatic.net/1000280685/product/go_3_d83ae4858e26429f9b23d6200d8d681c_large.jpg"
        ],
        "productName": "LULLABY",
        "productDescription": "Giường 1m8",
        "description": "<p><strong>M&agrave;u sắc: </strong>Xanh đậu</p><p><strong>K&iacute;ch thước sản phẩm: </strong>D100x R35 cm</p><p><strong>M&ocirc; tả sản phẩm:</strong> Vỏ gối được thiết kế c&oacute; kho&aacute; k&eacute;o dễ th&aacute;o vỏ hoặc lồng ruột gối.&nbsp;</p><p><strong>Chất liệu:&nbsp;</strong>100% Cotton 300 thread count</p><p><strong>Hướng dẫn sử dụng:</strong><br />- Kh&ocirc;ng n&ecirc;n ng&acirc;m sản phẩm.<br />- Kh&ocirc;ng giặt sản phẩm với c&aacute;c loại ho&aacute; chất c&oacute; chất tẩy mạnh.<br />- N&ecirc;n giặt bằng tay/giặt m&aacute;y chế độ nhẹ v&agrave; nhiệt độ b&igrave;nh thường.<br />- N&ecirc;n lật mặt tr&aacute;i sản phẩm, giặt ri&ecirc;ng theo m&agrave;u v&agrave; b&ecirc;n trong t&uacute;i giặt.<br />- N&ecirc;n phơi sản phẩm ở nơi tho&aacute;ng m&aacute;t, tr&aacute;nh &aacute;nh nắng trực tiếp.<br />- N&ecirc;n sấy kh&ocirc; hoặc ủi với nhiệt độ nhỏ hơn 110 độ C.<br />- Lưu &yacute;: Kh&ocirc;ng được ủi c&aacute;c sản phẩm chần g&ograve;n.</p><p>&nbsp;</p>",
        "price": "10190000",
        "priceDiscount": "",
        "wareHouse": "100"
    },
    {
        "id": "product40",
        "imgMain": "https://file.hstatic.net/1000280685/collection/coba_hong_2_b495df9036d84fb0b599ffcb05d4e766_medium.png",
        "imgHover": "https://product.hstatic.net/1000280685/product/tencel_magnet_trang_xamnhat__10__d8799c0cf4e84ca8b1fb44aa0e1eb0cd_large.png",
        "imgDemo": [
            "https://file.hstatic.net/1000280685/collection/coba_hong_2_b495df9036d84fb0b599ffcb05d4e766_medium.png",

            "https://product.hstatic.net/1000280685/product/tencel_magnet_trang_xamnhat__10__d8799c0cf4e84ca8b1fb44aa0e1eb0cd_large.png"
        ],
        "productName": "HANO",
        "productDescription": "Giường 1m6",
        "description": "<p><strong>M&agrave;u sắc: </strong>Xanh đậu</p><p><strong>K&iacute;ch thước sản phẩm: </strong>D100x R35 cm</p><p><strong>M&ocirc; tả sản phẩm:</strong> Vỏ gối được thiết kế c&oacute; kho&aacute; k&eacute;o dễ th&aacute;o vỏ hoặc lồng ruột gối.&nbsp;</p><p><strong>Chất liệu:&nbsp;</strong>100% Cotton 300 thread count</p><p><strong>Hướng dẫn sử dụng:</strong><br />- Kh&ocirc;ng n&ecirc;n ng&acirc;m sản phẩm.<br />- Kh&ocirc;ng giặt sản phẩm với c&aacute;c loại ho&aacute; chất c&oacute; chất tẩy mạnh.<br />- N&ecirc;n giặt bằng tay/giặt m&aacute;y chế độ nhẹ v&agrave; nhiệt độ b&igrave;nh thường.<br />- N&ecirc;n lật mặt tr&aacute;i sản phẩm, giặt ri&ecirc;ng theo m&agrave;u v&agrave; b&ecirc;n trong t&uacute;i giặt.<br />- N&ecirc;n phơi sản phẩm ở nơi tho&aacute;ng m&aacute;t, tr&aacute;nh &aacute;nh nắng trực tiếp.<br />- N&ecirc;n sấy kh&ocirc; hoặc ủi với nhiệt độ nhỏ hơn 110 độ C.<br />- Lưu &yacute;: Kh&ocirc;ng được ủi c&aacute;c sản phẩm chần g&ograve;n.</p><p>&nbsp;</p>",
        "price": "12590000",
        "priceDiscount": "",
        "wareHouse": "100"
    }
]
